setup.cfg
setup.py
lccv/__init__.py
lccv/lccv.py
lccv.egg-info/PKG-INFO
lccv.egg-info/SOURCES.txt
lccv.egg-info/dependency_links.txt
lccv.egg-info/requires.txt
lccv.egg-info/top_level.txt